school_sdk/__init__.py
school_sdk/config.py
school_sdk/type.py
school_sdk/utils.py
school_sdk/PyRsa/__init__.py
school_sdk/PyRsa/pyb64.py
school_sdk/PyRsa/pyjsbn.py
school_sdk/PyRsa/pyrng.py
school_sdk/PyRsa/pyrsa.py
school_sdk/PyRsa/tools.py
school_sdk/check_code/__init__.py
school_sdk/check_code/captcha_setting.py
school_sdk/check_code/dataset.py
school_sdk/check_code/model.pkl
school_sdk/check_code/model.py
school_sdk/check_code/predict.py
school_sdk/check_code/type.py
school_sdk/client/__init__.py
school_sdk/client/base.py
school_sdk/client/exceptions.py
school_sdk/client/utils.py
school_sdk/client/api/__init__.py
school_sdk/client/api/check.py
school_sdk/client/api/class_schedule.py
school_sdk/client/api/login.py
school_sdk/client/api/schedule_parse.py
school_sdk/client/api/schedules.py
school_sdk/client/api/score.py
school_sdk/client/api/user_info.py
school_sdk/session/__init__.py
school_sdk-1.7.1.dist-info/LICENSE
school_sdk-1.7.1.dist-info/METADATA
school_sdk-1.7.1.dist-info/WHEEL
school_sdk-1.7.1.dist-info/top_level.txt
school_sdk-1.7.1.dist-info/RECORD
