Metadata-Version: 2.1
Name: school-sdk
Version: 1.7.1
Summary: zf School SDK for Python
Home-page: https://github.com/Farmer-chong/new-school-sdk
Author: farmer.chillax
Author-email: farmer-chong@qq.com
License: MIT
Platform: any
Classifier: Environment :: Web Environment
Classifier: Intended Audience :: Developers
Classifier: License :: OSI Approved :: MIT License
Classifier: Operating System :: OS Independent
Classifier: Programming Language :: Python :: 3.8
Classifier: Topic :: Internet :: WWW/HTTP :: Dynamic Content
Classifier: Topic :: Software Development :: Libraries :: Python Modules
License-File: LICENSE
Requires-Dist: requests
Requires-Dist: pyquery
Requires-Dist: bs4
Requires-Dist: Pillow
Requires-Dist: fake-headers
Requires-Dist: torch
Requires-Dist: torchvision
